fetchcreds/__init__.py
fetchcreds/test.py
fetchcreds-0.0.1.dist-info/LICENSE
fetchcreds-0.0.1.dist-info/METADATA
fetchcreds-0.0.1.dist-info/WHEEL
fetchcreds-0.0.1.dist-info/top_level.txt
fetchcreds-0.0.1.dist-info/RECORD
